redicrypt/__init__.py
redicrypt/client.py
redicrypt_py-0.3.1.dist-info/LICENSE
redicrypt_py-0.3.1.dist-info/WHEEL
redicrypt_py-0.3.1.dist-info/METADATA
redicrypt_py-0.3.1.dist-info/RECORD
