Metadata-Version: 2.1
Name: redicrypt-py
Version: 0.3.1
Summary: A python library for redicrypt
License: MIT
Author: Chayim Kirshen
Author-email: c@kirshen.com
Requires-Python: >=3.6,<4.0
Classifier: Development Status :: 4 - Beta
Classifier: Intended Audience :: Developers
Classifier: License :: OSI Approved :: BSD License
Classifier: License :: OSI Approved :: MIT License
Classifier: Programming Language :: Python
Classifier: Programming Language :: Python :: 3
Classifier: Programming Language :: Python :: 3.10
Classifier: Programming Language :: Python :: 3.6
Classifier: Programming Language :: Python :: 3.7
Classifier: Programming Language :: Python :: 3.8
Classifier: Programming Language :: Python :: 3.9
Classifier: Topic :: Encryption
Requires-Dist: redis (>=3.5.3,<4.0.0)
